synchronizer_rpc-0.1.3.dist-info/LICENSE
synchronizer_rpc-0.1.3.dist-info/METADATA
synchronizer_rpc-0.1.3.dist-info/RECORD
synchronizer_rpc-0.1.3.dist-info/WHEEL
synchronizer_rpc/__init__.pyc
synchronizer_rpc/__init__.pyi
synchronizer_rpc/data/CStatus.pyc
synchronizer_rpc/data/CStatus.pyi
synchronizer_rpc/data/EnumDefine.pyc
synchronizer_rpc/data/EnumDefine.pyi
synchronizer_rpc/data/__init__.pyc
synchronizer_rpc/data/__init__.pyi
synchronizer_rpc/policy/POLICY.pyc
synchronizer_rpc/policy/POLICY.pyi
synchronizer_rpc/policy/__init__.pyc
synchronizer_rpc/policy/__init__.pyi
synchronizer_rpc/proto/__init__.pyc
synchronizer_rpc/proto/__init__.pyi
synchronizer_rpc/proto/syncProc_pb2.pyc
synchronizer_rpc/proto/syncProc_pb2.pyi
synchronizer_rpc/proto/syncProc_pb2_grpc.pyc
synchronizer_rpc/proto/syncProc_pb2_grpc.pyi
synchronizer_rpc/proxy/ProxyGRPC.pyc
synchronizer_rpc/proxy/ProxyGRPC.pyi
synchronizer_rpc/proxy/SVCConsumer.pyc
synchronizer_rpc/proxy/SVCConsumer.pyi
synchronizer_rpc/proxy/__init__.pyc
synchronizer_rpc/proxy/__init__.pyi
synchronizer_rpc/proxy/service/StatusCum.pyc
synchronizer_rpc/proxy/service/StatusCum.pyi
synchronizer_rpc/proxy/service/__init__.pyc
synchronizer_rpc/proxy/service/__init__.pyi
synchronizer_rpc/stub/SVCProvider.pyc
synchronizer_rpc/stub/SVCProvider.pyi
synchronizer_rpc/stub/StubGRPC.pyc
synchronizer_rpc/stub/StubGRPC.pyi
synchronizer_rpc/stub/__init__.pyc
synchronizer_rpc/stub/__init__.pyi
synchronizer_rpc/stub/service/StatusPvd.pyc
synchronizer_rpc/stub/service/StatusPvd.pyi
synchronizer_rpc/stub/service/__init__.pyc
synchronizer_rpc/stub/service/__init__.pyi
