Metadata-Version: 2.1
Name: synchronizer-rpc
Version: 0.1.3
Summary: 
Author: irradiance
Author-email: irradiance@gmail.com
Requires-Python: >=3.8,<4.0
Classifier: Programming Language :: Python :: 3
Classifier: Programming Language :: Python :: 3.8
Classifier: Programming Language :: Python :: 3.9
Classifier: Programming Language :: Python :: 3.10
Classifier: Programming Language :: Python :: 3.11
Classifier: Programming Language :: Python :: 3.12
Classifier: Programming Language :: Python :: 3.13
Requires-Dist: chardet (>=5.2.0,<6.0.0)
Requires-Dist: grpcio (>=1.69.0,<2.0.0)
Requires-Dist: grpcio-tools (>=1.69.0,<2.0.0)
Requires-Dist: libuseful (>=0.4.6,<0.5.0)
Requires-Dist: psutil (>=6.1.1,<7.0.0)
Requires-Dist: python-dateutil (>=2.9.0.post0,<3.0.0)
Requires-Dist: retry (>=0.9.2,<0.10.0)
Requires-Dist: tabulate (>=0.9.0,<0.10.0)
